lds/__init__.py
lds/lds.py
lds-0.0.1.dist-info/DESCRIPTION.rst
lds-0.0.1.dist-info/METADATA
lds-0.0.1.dist-info/RECORD
lds-0.0.1.dist-info/WHEEL
lds-0.0.1.dist-info/metadata.json
lds-0.0.1.dist-info/top_level.txt
