Metadata-Version: 2.0
Name: lds
Version: 0.0.1
Summary: A package written in Python that mimics some of the functionality provided by MongoDB.
Home-page: https://github.com/sbalaji1996/local-document-store
Author: Srinand Balaji
Author-email: srinand@berkeley.edu
License: UNKNOWN
Download-URL: https://github.com/sbalaji1996/local-document-store/archive/0.0.1.tar.gz
Keywords: json,document,in-memory,mongodb
Platform: UNKNOWN
